.gitignore
.pylintrc
.readthedocs.yml
CODE_OF_CONDUCT.md
LICENSE
README.rst
azurecustomvision_prediction.py
requirements.txt
setup.py
.github/workflows/build.yml
.github/workflows/release.yml
circuitpython_azurecustomvision_prediction.egg-info/PKG-INFO
circuitpython_azurecustomvision_prediction.egg-info/SOURCES.txt
circuitpython_azurecustomvision_prediction.egg-info/dependency_links.txt
circuitpython_azurecustomvision_prediction.egg-info/requires.txt
circuitpython_azurecustomvision_prediction.egg-info/top_level.txt
docs/api.rst
docs/conf.py
docs/examples.rst
docs/index.rst
docs/_static/favicon.ico
examples/customvision_prediction_imageclassification_camera.py
examples/customvision_prediction_objectdetection_camera.py
examples/customvision_simpletest.py