Metadata-Version: 2.1
Name: circuitpython-azurecustomvision-prediction
Version: 0.2.0
Summary: CircuitPython prediction library for the Azure custom vision SDK
Home-page: https://github.com/JimBobBennett/CircuitPython_azurecustomvision_prediction
Author: Jim Bennett
Author-email: jim.bennett@microsoft.com
License: MIT
Keywords: adafruit blinka circuitpython micropython circuitpython-azurecustomvision azure ai cognitive-services custom-vision
Platform: UNKNOWN
Classifier: Development Status :: 3 - Alpha
Classifier: Intended Audience :: Developers
Classifier: Topic :: Software Development :: Libraries
Classifier: Topic :: System :: Hardware
Classifier: License :: OSI Approved :: MIT License
Classifier: Programming Language :: Python :: 3
Classifier: Programming Language :: Python :: 3.4
Classifier: Programming Language :: Python :: 3.5
